{
    "version":  "1.8.0",
    "downloadUrl":  "https://github.com/7Seb4s/EPR-UDPATES/releases/download/v1.8.0/ERP-Calzado-Piolito-1.8.0.exe",
    "size":  93563904,
    "sha256":  "68c49172a57a048b6c529b9695248ce25514c49c83294f1da3eec84f9cd6bd86",
    "notes":  [
                  "Tarjetas de Control por lotes de 5 pares: al imprimir las tarjetas de Produccion (tanto la individual como las compactas de 4 por hoja) ahora sale una tarjeta por cada lote de 5 pares, con las tallas que le tocan a ese lote y los cuponcitos con los pares del lote. Las tallas se descuentan de la curva de menor a mayor, asi que un lote puede mezclar dos tallas y la suma de todos los lotes reconstruye la curva exacta. El resto impar se suma al ultimo lote (41 pares = 7 lotes de 5 y uno de 6). La Orden de Produccion no se divide, es un solo documento: ahora incluye una seccion PLAN DE LOTES que detalla cuantas tarjetas saldran y con que tallas cada una. El PDF Consolidado muestra el numero de lotes de cada OP. Los lotes solo existen en el PDF: no cambia nada en la base de datos ni en las etapas de produccion."
              ]
}